basiccodeally/Dimensions.py
basiccodeally/Position.py
basiccodeally/ResourceManager.py
basiccodeally/SemanticVersion.py
basiccodeally/Singleton.py
basiccodeally/UnitTestBase.py
basiccodeally/__init__.py
basiccodeally/_version.py
basiccodeally/py.typed
basiccodeally-0.5.1.dist-info/LICENSE
basiccodeally-0.5.1.dist-info/METADATA
basiccodeally-0.5.1.dist-info/WHEEL
basiccodeally-0.5.1.dist-info/top_level.txt
basiccodeally-0.5.1.dist-info/RECORD
