Metadata-Version: 2.1
Name: basiccodeally
Version: 0.5.1
Summary: Humberto`s Basic Common Code
Home-page: https://github.com/hasii2011/basiccodeally
Author: Humberto A. Sanchez II
Author-email: Humberto.A.Sanchez.II@gmail.com
Maintainer: Humberto A. Sanchez II
Maintainer-email: humberto.a.sanchez.ii@gmail.com
License-File: LICENSE
Requires-Dist: Deprecated ~=1.2.14
